MingChioY/__init__.py
MingChioY/MingChioY/__init__.py
MingChioY/MingChioY/aboutMingChioY.py
MingChioY/MingChioY/helloMingChioY.py
MingChioY/cli/__init__.py
MingChioY/cli/main.py
MingChioY/resources/__init__.py
mingchioy-1.0.5.data/data/requirements.txt
mingchioy-1.0.5.dist-info/licenses/LICENSE
mingchioy-1.0.5.dist-info/METADATA
mingchioy-1.0.5.dist-info/WHEEL
mingchioy-1.0.5.dist-info/entry_points.txt
mingchioy-1.0.5.dist-info/top_level.txt
mingchioy-1.0.5.dist-info/RECORD
