Metadata-Version: 2.4
Name: MingChioY
Version: 1.0.5
Summary: Python tools MingChioY, updating!
Home-page: https://pypi.org/project/MingChioY/
Author: MingChioY
Author-email: Chiyuan.jinggg@gmail.com
Classifier: Programming Language :: Python :: 3
Classifier: License :: OSI Approved :: MIT License
Classifier: Operating System :: OS Independent
Requires-Python: >=3.6
License-File: LICENSE
Requires-Dist: setuptools~=78.1.1
Requires-Dist: click~=8.2.1
Dynamic: author
Dynamic: author-email
Dynamic: classifier
Dynamic: description
Dynamic: description-content-type
Dynamic: home-page
Dynamic: license-file
Dynamic: requires-dist
Dynamic: requires-python
Dynamic: summary
